simple_maps/__init__.py
simple_maps/__main__.py
simple_maps/cartes.py
simple_maps/cli.py
simple_maps/util.py
simple_maps-0.2.0.dist-info/WHEEL
simple_maps-0.2.0.dist-info/entry_points.txt
simple_maps-0.2.0.dist-info/METADATA
simple_maps-0.2.0.dist-info/RECORD
