Metadata-Version: 2.4
Name: simple-maps
Version: 0.2.0
Summary: Tool to create maps with markers using cartes.io API
Keywords: map,cli,cartes,api
Author: Julio Batista Silva
Author-email: Julio Batista Silva <python@juliobs.com>
License-Expression: MIT
Classifier: Development Status :: 4 - Beta
Classifier: Environment :: Console
Classifier: Intended Audience :: Developers
Classifier: License :: OSI Approved :: MIT License
Classifier: Operating System :: OS Independent
Classifier: Programming Language :: Python :: 3
Classifier: Topic :: Internet :: WWW/HTTP :: Dynamic Content
Classifier: Topic :: Software Development :: Libraries :: Python Modules
Requires-Dist: httpx>=0.28.1
Requires-Dist: pydantic>=2.12.5
Requires-Dist: typer>=0.21.1
Requires-Python: >=3.14, <4
Project-URL: Homepage, https://juliobs.com/projects/simple-maps/
Project-URL: Documentation, https://github.com/jbsilva/simple-maps
Project-URL: Repository, https://github.com/jbsilva/simple-maps
Project-URL: Issues, https://github.com/jbsilva/simple-maps/issues
